102203525_TOPSIS/102203525.py
102203525_TOPSIS/__init__.py
TOPSIS/102203525.py
TOPSIS/__init__.py
TOPSIS/codee.py
102203525_TOPSIS-0.1.3.dist-info/METADATA
102203525_TOPSIS-0.1.3.dist-info/WHEEL
102203525_TOPSIS-0.1.3.dist-info/entry_points.txt
102203525_TOPSIS-0.1.3.dist-info/top_level.txt
102203525_TOPSIS-0.1.3.dist-info/RECORD
