Metadata-Version: 2.1
Name: 102203525-TOPSIS
Version: 0.1.3
Summary: A Python package for TOPSIS (Technique for Order of Preference by Similarity to Ideal Solution)
Requires-Dist: numpy
Requires-Dist: pandas
